LICENSE
README.md
setup.py
blur_detector/__init__.py
blur_detector.egg-info/PKG-INFO
blur_detector.egg-info/SOURCES.txt
blur_detector.egg-info/dependency_links.txt
blur_detector.egg-info/requires.txt
blur_detector.egg-info/top_level.txt