Metadata-Version: 2.1
Name: blur-detector
Version: 0.0.5
Summary: Uses discrete cosine transform coefficients at multiple scales and uses max pooling on the high frequency coefficients to get the sharp areas in an image.
Home-page: https://github.com/Utkarsh-Deshmukh/Spatially-Varying-Blur-Detection-python
Download-URL: https://github.com/Utkarsh-Deshmukh/Spatially-Varying-Blur-Detection-python/archive/refs/heads/main.zip
Author: utkarsh-deshmukh
Author-email: utkarsh.deshmukh@gmail.com
License: BSD 2-Clause "Simplified" License
Keywords: Spatially Varying Blur Detection
Classifier: Programming Language :: Python :: 3
Classifier: License :: OSI Approved :: BSD License
Classifier: Operating System :: OS Independent
License-File: LICENSE
